telemetry_producer/__init__.py
telemetry_producer/_version.py
telemetry_producer/application.py
telemetry_producer/handlers.py
telemetry_producer-0.1.3.data/data/etc/jupyter/jupyter_notebook_config.d/telemetry_producer.json
telemetry_producer-0.1.3.data/data/etc/jupyter/jupyter_server_config.d/telemetry_producer.json
telemetry_producer-0.1.3.data/data/share/jupyter/labextensions/telemetry-producer/package.json
telemetry_producer-0.1.3.data/data/share/jupyter/labextensions/telemetry-producer/static/747.77574f601f7b37856a0f.js
telemetry_producer-0.1.3.data/data/share/jupyter/labextensions/telemetry-producer/static/8.419f39ceb899796439d2.js
telemetry_producer-0.1.3.data/data/share/jupyter/labextensions/telemetry-producer/static/remoteEntry.8ebc6c463dd57e6074e6.js
telemetry_producer-0.1.3.data/data/share/jupyter/labextensions/telemetry-producer/static/style.js
telemetry_producer-0.1.3.data/data/share/jupyter/labextensions/telemetry-producer/static/third-party-licenses.json
telemetry_producer-0.1.3.data/data/share/jupyter/labextensions/telemetry-producer/install.json
telemetry_producer-0.1.3.dist-info/METADATA
telemetry_producer-0.1.3.dist-info/WHEEL
telemetry_producer-0.1.3.dist-info/licenses/LICENSE
telemetry_producer-0.1.3.dist-info/RECORD
